kori.py
kori-0.0.2.dist-info/LICENSE
kori-0.0.2.dist-info/METADATA
kori-0.0.2.dist-info/WHEEL
kori-0.0.2.dist-info/top_level.txt
kori-0.0.2.dist-info/RECORD
