Metadata-Version: 2.1
Name: kori
Version: 0.0.2
Summary: kori!
Home-page: UNKNOWN
Author: UNKNOWN
Author-email: UNKNOWN
License: UNKNOWN
Platform: UNKNOWN
